nshutils/__init__.py
nshutils/__init__.pyi
nshutils/_pytree_type_dynamic.py
nshutils/_tree_util.py
nshutils/actsave/__init__.py
nshutils/actsave/_loader.py
nshutils/actsave/_saver.py
nshutils/collections.py
nshutils/config.py
nshutils/debug/__init__.py
nshutils/debug/_assert.py
nshutils/debug/_config.py
nshutils/debug/_lightning.py
nshutils/display.py
nshutils/logging.py
nshutils/lovely/__init__.py
nshutils/lovely/_base.py
nshutils/lovely/_monkey_patch_all.py
nshutils/lovely/config.py
nshutils/lovely/jax_.py
nshutils/lovely/numpy_.py
nshutils/lovely/pprint_.py
nshutils/lovely/torch_.py
nshutils/lovely/utils.py
nshutils/snoop.py
nshutils/typecheck.py
nshutils-0.38.6.dist-info/WHEEL
nshutils-0.38.6.dist-info/METADATA
nshutils-0.38.6.dist-info/RECORD
