Metadata-Version: 2.3
Name: nshutils
Version: 0.38.6
Summary: 
Author: Nima Shoghi
Author-email: Nima Shoghi <nimashoghi@gmail.com>
Requires-Dist: lazy-loader
Requires-Dist: numpy
Requires-Dist: typing-extensions
Requires-Dist: jaxtyping ; python_full_version >= '3.10'
Requires-Dist: beartype ; python_full_version >= '3.10'
Requires-Dist: wadler-lindig ; python_full_version >= '3.10'
Requires-Dist: uuid7
Requires-Dist: pysnooper ; extra == 'extra'
Requires-Dist: rich[jupyter] ; extra == 'extra'
Requires-Dist: treescope ; python_full_version >= '3.10' and extra == 'extra'
Requires-Dist: rich[jupyter] ; extra == 'pprint'
Requires-Dist: treescope ; python_full_version >= '3.10' and extra == 'pprint'
Requires-Dist: pysnooper ; extra == 'snoop'
Requires-Python: >=3.10, <4.0
Project-URL: homepage, https://github.com/nimashoghi/nshutils
Provides-Extra: extra
Provides-Extra: pprint
Provides-Extra: snoop
